Workbook

Sheet Notes
A1: MT6102 · 12-Month Earnings Forecast (before OPEX)
A2: USD 250m fleet: 2× MR + 1× Aframax + 2× Kamsarmax · data cut-off 12 Sep 2026 (Clarksons SIN) · forecast window Oct 2026 – Sep 2027
B4: Core formula
B5: Annual earnings (before OPEX) per ship = Daily TCE / TC rate × Operating days × (1 − commission)
B6: Operating days = 365 − 15 off-hire days = 350 (covers the first special survey/drydock due on the 5-yr-old MRs).
B7: Fleet earnings = Σ 5 ships. Return on capital = Fleet earnings ÷ USD 250m.
B9: Why three scenarios — and why only two ships move
B10: 3 ships (MR#1 SUNCOR 1yr, Aframax AET-type 3yr, Kamsarmax#1 CNR 12m) are on fixed time charters → their income is identical in every scenario.
B11: 2 ships (MR#2, Kamsarmax#2) trade spot → their TCE is the only variable. Bear = 2025 average earnings; Base = last-done 1yr TC as spot-TCE proxy; Bull = current spot holds.
B12: Expected value = probability-weighted average of the three scenarios (weights on Inputs sheet).
B14: Sheet guide
B15: Inputs — every number used, with its source. Yellow cells = assumptions you may change. Blue text = hard-coded input; black = formula; green = link from another sheet.
B16: Forecast — per-ship annual earnings, three scenarios, expected value, return on capital, after-OPEX reference.
B17: Monthly — 12-month month-by-month earnings for the scenario chosen in Inputs!C26 (1 = Bear, 2 = Base, 3 = Bull).
... B25: 4. 'Before OPEX' = TCE level. For TC ships the charterer pays voyage costs; for spot ships the TCE already nets out bunkers, port and canal costs.

Sheet Forecast
A1: 12-month earnings forecast — before OPEX
A2: Earnings = TCE × operating days × (1 − commission). Green = link to Inputs.
A4: # | B4: Ship | C4: Employment type | D4: Op. days | E4: Bear ($) | F4: Base ($) | G4: Bull ($)
A5: =Inputs!A5 -> 1 | B5: =Inputs!B5 -> MR #1 (50k dwt, ~5 yrs) | C5: Fixed TC | D5: =Inputs!$D$17 -> 350 | E5: =Inputs!F5*$D5*(1-Inputs!$D$18) -> 10500000 | F5: =Inputs!G5*$D5*(1-Inputs!$D$18) -> 10500000 | G5: =Inputs!H5*$D5*(1-Inputs!$D$18) -> 10500000
A6: =Inputs!A6 -> 2 | B6: =Inputs!B6 -> MR #2 (50k dwt, ~5 yrs) | C6: Spot | D6: =Inputs!$D$17 -> 350 | E6: =Inputs!F6*$D6*(1-Inputs!$D$18) -> 6650000 | F6: =Inputs!G6*$D6*(1-Inputs!$D$18) -> 9450000 | G6: =Inputs!H6*$D6*(1-Inputs!$D$18) -> 11550000
A7: =Inputs!A7 -> 3 | B7: =Inputs!B7 -> Aframax (109k dwt, 2018 Japan) | C7: Fixed TC | D7: =Inputs!$D$17 -> 350 | E7: =Inputs!F7*$D7*(1-Inputs!$D$18) -> 14000000 | F7: =Inputs!G7*$D7*(1-Inputs!$D$18) -> 14000000 | G7: =Inputs!H7*$D7*(1-Inputs!$D$18) -> 14000000
A8: =Inputs!A8 -> 4 | B8: =Inputs!B8 -> Kamsarmax #1 (82k, 2019 Japan) | C8: Fixed TC | D8: =Inputs!$D$17 -> 350 | E8: =Inputs!F8*$D8*(1-Inputs!$D$18) -> 7700000 | F8: =Inputs!G8*$D8*(1-Inputs!$D$18) -> 7700000 | G8: =Inputs!H8*$D8*(1-Inputs!$D$18) -> 7700000
A9: =Inputs!A9 -> 5 | B9: =Inputs!B9 -> Kamsarmax #2 (82k, 2015 Japan) | C9: Spot | D9: =Inputs!$D$17 -> 350 | E9: =Inputs!F9*$D9*(1-Inputs!$D$18) -> 4445000 | F9: =Inputs!G9*$D9*(1-Inputs!$D$18) -> 8050000 | G9: =Inputs!H9*$D9*(1-Inputs!$D$18) -> 9555000
B10: Fleet earnings before OPEX | E10: =SUM(E5:E9) -> 43295000 | F10: =SUM(F5:F9) -> 49700000 | G10: =SUM(G5:G9) -> 53305000
B11: of which fixed-TC (locked) | E11: =SUMIF($C$5:$C$9,"Fixed TC",E5:E9) -> 32200000 | F11: =SUMIF($C$5:$C$9,"Fixed TC",F5:F9) -> 32200000 | G11: =SUMIF($C$5:$C$9,"Fixed TC",G5:G9) -> 32200000
B12: of which spot (at risk) | E12: =SUMIF($C$5:$C$9,"Spot",E5:E9) -> 11095000 | F12: =SUMIF($C$5:$C$9,"Spot",F5:F9) -> 17500000 | G12: =SUMIF($C$5:$C$9,"Spot",G5:G9) -> 21105000
B13: Locked share of earnings | E13: =IF(E10=0,0,E11/E10) -> 0.74373484 | F13: =IF(F10=0,0,F11/F10) -> 0.64788732 | G13: =IF(G10=0,0,G11/G10) -> 0.60407091
B14: Return on capital (before OPEX) | E14: =E10/Inputs!$D$14 -> 0.17318 | F14: =F10/Inputs!$D$14 -> 0.1988 | G14: =G10/Inputs!$D$14 -> 0.21322
B15: Average fleet earnings ($/day) | E15: =E10/Inputs!$D$17 -> 123700 | F15: =F10/Inputs!$D$17 -> 142000 | G15: =G10/Inputs!$D$17 -> 152300
B17: Reference: after OPEX
B18: Fleet OPEX for the year ($) | E18: =Inputs!$D$19*Inputs!$D$17 -> 12796000 | F18: =Inputs!$D$19*Inputs!$D$17 -> 12796000 | G18: =Inputs!$D$19*Inputs!$D$17 -> 12796000
B19: Earnings after OPEX ($) | E19: =E10-E18 -> 30499000 | F19: =F10-F18 -> 36904000 | G19: =G10-G18 -> 40509000
B20: Return after OPEX | E20: =E19/Inputs!$D$14 -> 0.121996 | F20: =F19/Inputs!$D$14 -> 0.147616 | G20: =G19/Inputs!$D$14 -> 0.162036
B22: Expected (probability-weighted) forecast
B23: Scenario weight | E23: =Inputs!D21 -> 0.3 | F23: =Inputs!D22 -> 0.5 | G23: =Inputs!D23 -> 0.2
B24: Expected earnings before OPEX ($) | G24: =SUMPRODUCT(E10:G10,E23:G23) -> 48499500
B25: Expected return on capital | G25: =G24/Inputs!D14 -> 0.193998
B26: Expected earnings after OPEX ($) | G26: =G24-E18 -> 35703500
B27: Downside protection: Bear vs Base | G27: =E10/F10-1 -> -0.12887324
B29: Note: only MR #2 and Kamsarmax #2 change between scenarios; the three time-chartered ships earn the same in every case.

Sheet Inputs
A1: Inputs & assumptions
A2: Blue = hard-coded input · Yellow fill = key assumption you can change · all prices/rates = Clarksons SIN last-done, extracted 12 Sep 2026
A4: # | B4: Ship | C4: Type | D4: Purchase price ($) | E4: Employment | F4: Bear TCE ($/day) | G4: Base TCE ($/day) | H4: Bull TCE ($/day) | I4: Source (last-done fixture / sale)
A5: 1 | B5: MR #1 (50k dwt, ~5 yrs) | C5: MR product | D5: 50000000 | E5: 1-yr TC – SUNCOR | F5: 30000 | G5: 30000 | H5: 30000 | I5: TC: PS Imabari 52.8k, SUNCOR, 1yr @ $30,000/d (17 Aug 2026). Price: SIN 5-yr MR valuation series 47130 = $50.0m
A6: 2 | B6: MR #2 (50k dwt, ~5 yrs) | C6: MR product | D6: 50000000 | E6: Spot (ME/India → EAF, SE Asia) | F6: 19000 | G6: 27000 | H6: 33000 | I6: Base: Challenge Pollux 50k, EXXONMOBIL, 1yr @ $27,000/d (17 Aug 2026) as spot-TCE proxy. Spot ref: Baltic→USG WS105 (VITOL, 10 Sep). Bear/Bull: see Notes caveat 2
A7: 3 | B7: Aframax (109k dwt, 2018 Japan) | C7: Aframax crude | D7: 75000000 | E7: 3-yr TC (AET benchmark) | F7: 40000 | G7: 40000 | H7: 40000 | I7: TC: Torm Genesis 119k, AET, 3yr @ $40,000/d (31 Aug 2026). Price: Southern Reverence / Pusaka Borneo 2018 Japan @ $75.0m (May/Apr 2026)
A8: 4 | B8: Kamsarmax #1 (82k, 2019 Japan) | C8: Kamsarmax bulk | D8: 38000000 | E8: 12-m TC – CNR | F8: 22000 | G8: 22000 | H8: 22000 | I8: TC: Intensity 82k, CNR, 12m @ $22,000/d (7 Sep 2026). Price: Aquavita Aim 82k 2019 Oshima @ $38.0m (10 Aug 2026)
A9: 5 | B9: Kamsarmax #2 (82k, 2015 Japan) | C9: Kamsarmax bulk | D9: 32000000 | E9: Spot (Guinea bauxite, Aus coal, grain) | F9: 12700 | G9: 23000 | H9: 27300 | I9: Base: XH Hope 85k, CARGILL, 10-12m @ $23,000/d (3 Sep 2026). Spot ref: DBCT→Vizag coal $25.60/t (SAIL, 10 Sep) → see Voyage_TCE. Price: Medi Positano 2015 Japan @ $32.0m
B10: Fleet total | D10: =SUM(D5:D9) -> 245000000 | F10: =SUM(F5:F9) -> 123700 | G10: =SUM(G5:G9) -> 142000 | H10: =SUM(H5:H9) -> 152300
B11: Cash reserve | D11: =D14-D10 -> 5000000 | I11: Kept for counter-cyclical purchase + working capital (proposal p.1)
B13: General parameters
B14: Capital deployed ($) | D14: 250000000 | E14: Board mandate
B15: Days in forecast year | D15: 365 | E15: Oct 2026 – Sep 2027
B16: Off-hire days per ship | D16: 15 | E16: Industry convention: repairs, surveys, drydock (proposal p.8)
B17: Operating days per ship | D17: =D15-D16 -> 350 | E17: Formula
B18: Commission on gross hire (%) | D18: 0 | E18: 0% to match proposal gross figures; typical 3.75% (1.25% brokerage + 2.5% address)
B19: Fleet OPEX ($/day, 5 ships) | D19: 36560 | E19: Clarksons OPEX series 540687 / 540689 / 540683 (crew, insurance, R&M) — reference only
B21: Scenario weight – Bear | D21: 0.3 | E21: Group judgement: ceasefire / recession risk
B22: Scenario weight – Base | D22: 0.5 | E22: Group judgement: last-done fixtures persist
B23: Scenario weight – Bull | D23: 0.2 | E23: Group judgement: current spot strength persists 12 months
B24: Check: weights sum to 100% | D24: =IF(ROUND(SUM(D21:D23),6)=1,"OK","ERROR – weights ≠ 100%") -> OK
B26: Scenario shown on Monthly sheet | D26: 2 | E26: 1 = Bear · 2 = Base · 3 = Bull

Sheet Monthly
A1: Month-by-month earnings before OPEX
A2: Scenario per Inputs!D26. Monthly = TCE × calendar days × (operating days ÷ 365) × (1 − commission): off-hire spread evenly.
A3: Scenario shown: | B3: =CHOOSE(Inputs!D26,"Bear","Base","Bull") -> Base
A5: Ship | B5: TCE ($/day) | C5: Oct-26 | D5: Nov-26 | E5: Dec-26 | F5: Jan-27 | G5: Feb-27 | H5: Mar-27 | I5: Apr-27 | J5: May-27 | K5: Jun-27 | L5: Jul-27 | M5: Aug-27 | N5: Sep-27 | O5: 12-m total
A6: Calendar days | C6: 31 | D6: 30 | E6: 31 | F6: 31 | G6: 28 | H6: 31 | I6: 30 | J6: 31 | K6: 30 | L6: 31 | M6: 31 | N6: 30 | O6: =SUM(C6:N6) -> 365
A7: =Inputs!B5 -> MR #1 (50k dwt, ~5 yrs) | B7: =CHOOSE(Inputs!$D$26,Inputs!F5,Inputs!G5,Inputs!H5) -> 30000 | C7: =$B7*C$6*Inputs!$D$17/Inputs!$D$15*(1-Inputs!$D$18) -> 891780.82 | D7: =$B7*D$6*Inputs!$D$17/Inputs!$D$15*(1-Inputs!$D$18) -> 863013.7 | E7: =$B7*E$6*Inputs!$D$17/Inputs!$D$15*(1-Inputs!$D$18) -> 891780.82 | F7: =$B7*F$6*Inputs!$D$17/Inputs!$D$15*(1-Inputs!$D$18) -> 891780.82 | G7: =$B7*G$6*Inputs!$D$17/Inputs!$D$15*(1-Inputs!$D$18) -> 805479.45 | H7: =$B7*H$6*Inputs!$D$17/Inputs!$D$15*(1-Inputs!$D$18) -> 891780.82 | I7: =$B7*I$6*Inputs!$D$17/Inputs!$D$15*(1-Inputs!$D$18) -> 863013.7 | J7: =$B7*J$6*Inputs!$D$17/Inputs!$D$15*(1-Inputs!$D$18) -> 891780.82 | ... N7: =$B7*N$6*Inputs!$D$17/Inputs!$D$15*(1-Inputs!$D$18) -> 863013.7 | O7: =SUM(C7:N7) -> 10500000
A8: =Inputs!B6 -> MR #2 (50k dwt, ~5 yrs) | B8: =CHOOSE(Inputs!$D$26,Inputs!F6,Inputs!G6,Inputs!H6) -> 27000 | C8: =$B8*C$6*Inputs!$D$17/Inputs!$D$15*(1-Inputs!$D$18) -> 802602.74 | D8: =$B8*D$6*Inputs!$D$17/Inputs!$D$15*(1-Inputs!$D$18) -> 776712.33 | E8: =$B8*E$6*Inputs!$D$17/Inputs!$D$15*(1-Inputs!$D$18) -> 802602.74 | F8: =$B8*F$6*Inputs!$D$17/Inputs!$D$15*(1-Inputs!$D$18) -> 802602.74 | G8: =$B8*G$6*Inputs!$D$17/Inputs!$D$15*(1-Inputs!$D$18) -> 724931.51 | H8: =$B8*H$6*Inputs!$D$17/Inputs!$D$15*(1-Inputs!$D$18) -> 802602.74 | I8: =$B8*I$6*Inputs!$D$17/Inputs!$D$15*(1-Inputs!$D$18) -> 776712.33 | J8: =$B8*J$6*Inputs!$D$17/Inputs!$D$15*(1-Inputs!$D$18) -> 802602.74 | ... N8: =$B8*N$6*Inputs!$D$17/Inputs!$D$15*(1-Inputs!$D$18) -> 776712.33 | O8: =SUM(C8:N8) -> 9450000
A9: =Inputs!B7 -> Aframax (109k dwt, 2018 Japan) | B9: =CHOOSE(Inputs!$D$26,Inputs!F7,Inputs!G7,Inputs!H7) -> 40000 | C9: =$B9*C$6*Inputs!$D$17/Inputs!$D$15*(1-Inputs!$D$18) -> 1189041.1 | D9: =$B9*D$6*Inputs!$D$17/Inputs!$D$15*(1-Inputs!$D$18) -> 1150684.9 | E9: =$B9*E$6*Inputs!$D$17/Inputs!$D$15*(1-Inputs!$D$18) -> 1189041.1 | F9: =$B9*F$6*Inputs!$D$17/Inputs!$D$15*(1-Inputs!$D$18) -> 1189041.1 | G9: =$B9*G$6*Inputs!$D$17/Inputs!$D$15*(1-Inputs!$D$18) -> 1073972.6 | H9: =$B9*H$6*Inputs!$D$17/Inputs!$D$15*(1-Inputs!$D$18) -> 1189041.1 | I9: =$B9*I$6*Inputs!$D$17/Inputs!$D$15*(1-Inputs!$D$18) -> 1150684.9 | J9: =$B9*J$6*Inputs!$D$17/Inputs!$D$15*(1-Inputs!$D$18) -> 1189041.1 | ... N9: =$B9*N$6*Inputs!$D$17/Inputs!$D$15*(1-Inputs!$D$18) -> 1150684.9 | O9: =SUM(C9:N9) -> 14000000
A10: =Inputs!B8 -> Kamsarmax #1 (82k, 2019 Japan) | B10: =CHOOSE(Inputs!$D$26,Inputs!F8,Inputs!G8,Inputs!H8) -> 22000 | C10: =$B10*C$6*Inputs!$D$17/Inputs!$D$15*(1-Inputs!$D$18) -> 653972.6 | D10: =$B10*D$6*Inputs!$D$17/Inputs!$D$15*(1-Inputs!$D$18) -> 632876.71 | E10: =$B10*E$6*Inputs!$D$17/Inputs!$D$15*(1-Inputs!$D$18) -> 653972.6 | F10: =$B10*F$6*Inputs!$D$17/Inputs!$D$15*(1-Inputs!$D$18) -> 653972.6 | G10: =$B10*G$6*Inputs!$D$17/Inputs!$D$15*(1-Inputs!$D$18) -> 590684.93 | H10: =$B10*H$6*Inputs!$D$17/Inputs!$D$15*(1-Inputs!$D$18) -> 653972.6 | I10: =$B10*I$6*Inputs!$D$17/Inputs!$D$15*(1-Inputs!$D$18) -> 632876.71 | J10: =$B10*J$6*Inputs!$D$17/Inputs!$D$15*(1-Inputs!$D$18) -> 653972.6 | ... N10: =$B10*N$6*Inputs!$D$17/Inputs!$D$15*(1-Inputs!$D$18) -> 632876.71 | O10: =SUM(C10:N10) -> 7700000
A11: =Inputs!B9 -> Kamsarmax #2 (82k, 2015 Japan) | B11: =CHOOSE(Inputs!$D$26,Inputs!F9,Inputs!G9,Inputs!H9) -> 23000 | C11: =$B11*C$6*Inputs!$D$17/Inputs!$D$15*(1-Inputs!$D$18) -> 683698.63 | D11: =$B11*D$6*Inputs!$D$17/Inputs!$D$15*(1-Inputs!$D$18) -> 661643.84 | E11: =$B11*E$6*Inputs!$D$17/Inputs!$D$15*(1-Inputs!$D$18) -> 683698.63 | F11: =$B11*F$6*Inputs!$D$17/Inputs!$D$15*(1-Inputs!$D$18) -> 683698.63 | G11: =$B11*G$6*Inputs!$D$17/Inputs!$D$15*(1-Inputs!$D$18) -> 617534.25 | H11: =$B11*H$6*Inputs!$D$17/Inputs!$D$15*(1-Inputs!$D$18) -> 683698.63 | I11: =$B11*I$6*Inputs!$D$17/Inputs!$D$15*(1-Inputs!$D$18) -> 661643.84 | J11: =$B11*J$6*Inputs!$D$17/Inputs!$D$15*(1-Inputs!$D$18) -> 683698.63 | ... N11: =$B11*N$6*Inputs!$D$17/Inputs!$D$15*(1-Inputs!$D$18) -> 661643.84 | O11: =SUM(C11:N11) -> 8050000
A12: Fleet total | C12: =SUM(C7:C11) -> 4221095.9 | D12: =SUM(D7:D11) -> 4084931.5 | E12: =SUM(E7:E11) -> 4221095.9 | F12: =SUM(F7:F11) -> 4221095.9 | G12: =SUM(G7:G11) -> 3812602.7 | H12: =SUM(H7:H11) -> 4221095.9 | I12: =SUM(I7:I11) -> 4084931.5 | J12: =SUM(J7:J11) -> 4221095.9 | ... O12: =SUM(O7:O11) -> 49700000
A13: Fixed-TC ships (MR#1, Aframax, Kams#1) | C13: =C7+C9+C10 -> 2734794.5 | D13: =D7+D9+D10 -> 2646575.3 | E13: =E7+E9+E10 -> 2734794.5 | F13: =F7+F9+F10 -> 2734794.5 | G13: =G7+G9+G10 -> 2470137 | H13: =H7+H9+H10 -> 2734794.5 | I13: =I7+I9+I10 -> 2646575.3 | J13: =J7+J9+J10 -> 2734794.5 | ... O13: =O7+O9+O10 -> 32200000
A14: Spot ships (MR#2, Kams#2) | C14: =C8+C11 -> 1486301.4 | D14: =D8+D11 -> 1438356.2 | E14: =E8+E11 -> 1486301.4 | F14: =F8+F11 -> 1486301.4 | G14: =G8+G11 -> 1342465.8 | H14: =H8+H11 -> 1486301.4 | I14: =I8+I11 -> 1438356.2 | J14: =J8+J11 -> 1486301.4 | ... O14: =O8+O11 -> 17500000
A15: Cumulative fleet earnings | C15: =C12 -> 4221095.9 | D15: =C15+D12 -> 8306027.4 | E15: =D15+E12 -> 12527123 | F15: =E15+F12 -> 16748219 | G15: =F15+G12 -> 20560822 | H15: =G15+H12 -> 24781918 | I15: =H15+I12 -> 28866849 | J15: =I15+J12 -> 33087945 | K15: =J15+K12 -> 37172877 | ... N15: =M15+N12 -> 49700000
A16: Check vs Forecast sheet (should be 0) | O16: =ROUND(O12-INDEX(Forecast!E10:G10,Inputs!D26),0) -> 0

Sheet Sensitivity
A1: Sensitivity: fleet earnings before OPEX ($m) vs spot TCE of the two spot ships
A2: Fixed-TC ships held at contract rates. Rows = MR #2 spot TCE; columns = Kamsarmax #2 spot TCE.
A4: Fixed-TC earnings (constant) | B4: =Forecast!F11 -> 32200000
A6: MR#2 TCE ↓ / Kams#2 TCE → | B6: 10000 | C6: 13000 | D6: 16000 | E6: 19000 | F6: 23000 | G6: 27000 | H6: 31000 | I6: 35000
A7: 15000 | B7: =($B$4+($A7+B$6)*Inputs!$D$17*(1-Inputs!$D$18))/1000000 -> 40.95 | C7: =($B$4+($A7+C$6)*Inputs!$D$17*(1-Inputs!$D$18))/1000000 -> 42 | D7: =($B$4+($A7+D$6)*Inputs!$D$17*(1-Inputs!$D$18))/1000000 -> 43.05 | E7: =($B$4+($A7+E$6)*Inputs!$D$17*(1-Inputs!$D$18))/1000000 -> 44.1 | F7: =($B$4+($A7+F$6)*Inputs!$D$17*(1-Inputs!$D$18))/1000000 -> 45.5 | G7: =($B$4+($A7+G$6)*Inputs!$D$17*(1-Inputs!$D$18))/1000000 -> 46.9 | H7: =($B$4+($A7+H$6)*Inputs!$D$17*(1-Inputs!$D$18))/1000000 -> 48.3 | I7: =($B$4+($A7+I$6)*Inputs!$D$17*(1-Inputs!$D$18))/1000000 -> 49.7
A8: 18000 | B8: =($B$4+($A8+B$6)*Inputs!$D$17*(1-Inputs!$D$18))/1000000 -> 42 | C8: =($B$4+($A8+C$6)*Inputs!$D$17*(1-Inputs!$D$18))/1000000 -> 43.05 | D8: =($B$4+($A8+D$6)*Inputs!$D$17*(1-Inputs!$D$18))/1000000 -> 44.1 | E8: =($B$4+($A8+E$6)*Inputs!$D$17*(1-Inputs!$D$18))/1000000 -> 45.15 | F8: =($B$4+($A8+F$6)*Inputs!$D$17*(1-Inputs!$D$18))/1000000 -> 46.55 | G8: =($B$4+($A8+G$6)*Inputs!$D$17*(1-Inputs!$D$18))/1000000 -> 47.95 | H8: =($B$4+($A8+H$6)*Inputs!$D$17*(1-Inputs!$D$18))/1000000 -> 49.35 | I8: =($B$4+($A8+I$6)*Inputs!$D$17*(1-Inputs!$D$18))/1000000 -> 50.75
A9: 21000 | B9: =($B$4+($A9+B$6)*Inputs!$D$17*(1-Inputs!$D$18))/1000000 -> 43.05 | C9: =($B$4+($A9+C$6)*Inputs!$D$17*(1-Inputs!$D$18))/1000000 -> 44.1 | D9: =($B$4+($A9+D$6)*Inputs!$D$17*(1-Inputs!$D$18))/1000000 -> 45.15 | E9: =($B$4+($A9+E$6)*Inputs!$D$17*(1-Inputs!$D$18))/1000000 -> 46.2 | F9: =($B$4+($A9+F$6)*Inputs!$D$17*(1-Inputs!$D$18))/1000000 -> 47.6 | G9: =($B$4+($A9+G$6)*Inputs!$D$17*(1-Inputs!$D$18))/1000000 -> 49 | H9: =($B$4+($A9+H$6)*Inputs!$D$17*(1-Inputs!$D$18))/1000000 -> 50.4 | I9: =($B$4+($A9+I$6)*Inputs!$D$17*(1-Inputs!$D$18))/1000000 -> 51.8
A10: 24000 | B10: =($B$4+($A10+B$6)*Inputs!$D$17*(1-Inputs!$D$18))/1000000 -> 44.1 | C10: =($B$4+($A10+C$6)*Inputs!$D$17*(1-Inputs!$D$18))/1000000 -> 45.15 | D10: =($B$4+($A10+D$6)*Inputs!$D$17*(1-Inputs!$D$18))/1000000 -> 46.2 | E10: =($B$4+($A10+E$6)*Inputs!$D$17*(1-Inputs!$D$18))/1000000 -> 47.25 | F10: =($B$4+($A10+F$6)*Inputs!$D$17*(1-Inputs!$D$18))/1000000 -> 48.65 | G10: =($B$4+($A10+G$6)*Inputs!$D$17*(1-Inputs!$D$18))/1000000 -> 50.05 | H10: =($B$4+($A10+H$6)*Inputs!$D$17*(1-Inputs!$D$18))/1000000 -> 51.45 | I10: =($B$4+($A10+I$6)*Inputs!$D$17*(1-Inputs!$D$18))/1000000 -> 52.85
A11: 27000 | B11: =($B$4+($A11+B$6)*Inputs!$D$17*(1-Inputs!$D$18))/1000000 -> 45.15 | C11: =($B$4+($A11+C$6)*Inputs!$D$17*(1-Inputs!$D$18))/1000000 -> 46.2 | D11: =($B$4+($A11+D$6)*Inputs!$D$17*(1-Inputs!$D$18))/1000000 -> 47.25 | E11: =($B$4+($A11+E$6)*Inputs!$D$17*(1-Inputs!$D$18))/1000000 -> 48.3 | F11: =($B$4+($A11+F$6)*Inputs!$D$17*(1-Inputs!$D$18))/1000000 -> 49.7 | G11: =($B$4+($A11+G$6)*Inputs!$D$17*(1-Inputs!$D$18))/1000000 -> 51.1 | H11: =($B$4+($A11+H$6)*Inputs!$D$17*(1-Inputs!$D$18))/1000000 -> 52.5 | I11: =($B$4+($A11+I$6)*Inputs!$D$17*(1-Inputs!$D$18))/1000000 -> 53.9
A12: 30000 | B12: =($B$4+($A12+B$6)*Inputs!$D$17*(1-Inputs!$D$18))/1000000 -> 46.2 | C12: =($B$4+($A12+C$6)*Inputs!$D$17*(1-Inputs!$D$18))/1000000 -> 47.25 | D12: =($B$4+($A12+D$6)*Inputs!$D$17*(1-Inputs!$D$18))/1000000 -> 48.3 | E12: =($B$4+($A12+E$6)*Inputs!$D$17*(1-Inputs!$D$18))/1000000 -> 49.35 | F12: =($B$4+($A12+F$6)*Inputs!$D$17*(1-Inputs!$D$18))/1000000 -> 50.75 | G12: =($B$4+($A12+G$6)*Inputs!$D$17*(1-Inputs!$D$18))/1000000 -> 52.15 | H12: =($B$4+($A12+H$6)*Inputs!$D$17*(1-Inputs!$D$18))/1000000 -> 53.55 | I12: =($B$4+($A12+I$6)*Inputs!$D$17*(1-Inputs!$D$18))/1000000 -> 54.95
A13: 33000 | B13: =($B$4+($A13+B$6)*Inputs!$D$17*(1-Inputs!$D$18))/1000000 -> 47.25 | C13: =($B$4+($A13+C$6)*Inputs!$D$17*(1-Inputs!$D$18))/1000000 -> 48.3 | D13: =($B$4+($A13+D$6)*Inputs!$D$17*(1-Inputs!$D$18))/1000000 -> 49.35 | E13: =($B$4+($A13+E$6)*Inputs!$D$17*(1-Inputs!$D$18))/1000000 -> 50.4 | F13: =($B$4+($A13+F$6)*Inputs!$D$17*(1-Inputs!$D$18))/1000000 -> 51.8 | G13: =($B$4+($A13+G$6)*Inputs!$D$17*(1-Inputs!$D$18))/1000000 -> 53.2 | H13: =($B$4+($A13+H$6)*Inputs!$D$17*(1-Inputs!$D$18))/1000000 -> 54.6 | I13: =($B$4+($A13+I$6)*Inputs!$D$17*(1-Inputs!$D$18))/1000000 -> 56
A14: 36000 | B14: =($B$4+($A14+B$6)*Inputs!$D$17*(1-Inputs!$D$18))/1000000 -> 48.3 | C14: =($B$4+($A14+C$6)*Inputs!$D$17*(1-Inputs!$D$18))/1000000 -> 49.35 | D14: =($B$4+($A14+D$6)*Inputs!$D$17*(1-Inputs!$D$18))/1000000 -> 50.4 | E14: =($B$4+($A14+E$6)*Inputs!$D$17*(1-Inputs!$D$18))/1000000 -> 51.45 | F14: =($B$4+($A14+F$6)*Inputs!$D$17*(1-Inputs!$D$18))/1000000 -> 52.85 | G14: =($B$4+($A14+G$6)*Inputs!$D$17*(1-Inputs!$D$18))/1000000 -> 54.25 | H14: =($B$4+($A14+H$6)*Inputs!$D$17*(1-Inputs!$D$18))/1000000 -> 55.65 | I14: =($B$4+($A14+I$6)*Inputs!$D$17*(1-Inputs!$D$18))/1000000 -> 57.05
A15: 40000 | B15: =($B$4+($A15+B$6)*Inputs!$D$17*(1-Inputs!$D$18))/1000000 -> 49.7 | C15: =($B$4+($A15+C$6)*Inputs!$D$17*(1-Inputs!$D$18))/1000000 -> 50.75 | D15: =($B$4+($A15+D$6)*Inputs!$D$17*(1-Inputs!$D$18))/1000000 -> 51.8 | E15: =($B$4+($A15+E$6)*Inputs!$D$17*(1-Inputs!$D$18))/1000000 -> 52.85 | F15: =($B$4+($A15+F$6)*Inputs!$D$17*(1-Inputs!$D$18))/1000000 -> 54.25 | G15: =($B$4+($A15+G$6)*Inputs!$D$17*(1-Inputs!$D$18))/1000000 -> 55.65 | H15: =($B$4+($A15+H$6)*Inputs!$D$17*(1-Inputs!$D$18))/1000000 -> 57.05 | I15: =($B$4+($A15+I$6)*Inputs!$D$17*(1-Inputs!$D$18))/1000000 -> 58.45
A17: Same grid as return on USD 250m capital
A18: MR#2 TCE ↓ / Kams#2 TCE → | B18: =B6 -> 10000 | C18: =C6 -> 13000 | D18: =D6 -> 16000 | E18: =E6 -> 19000 | F18: =F6 -> 23000 | G18: =G6 -> 27000 | H18: =H6 -> 31000 | I18: =I6 -> 35000
A19: =A7 -> 15000 | B19: =B7*1000000/Inputs!$D$14 -> 0.1638 | C19: =C7*1000000/Inputs!$D$14 -> 0.168 | D19: =D7*1000000/Inputs!$D$14 -> 0.1722 | E19: =E7*1000000/Inputs!$D$14 -> 0.1764 | F19: =F7*1000000/Inputs!$D$14 -> 0.182 | G19: =G7*1000000/Inputs!$D$14 -> 0.1876 | H19: =H7*1000000/Inputs!$D$14 -> 0.1932 | I19: =I7*1000000/Inputs!$D$14 -> 0.1988
A20: =A8 -> 18000 | B20: =B8*1000000/Inputs!$D$14 -> 0.168 | C20: =C8*1000000/Inputs!$D$14 -> 0.1722 | D20: =D8*1000000/Inputs!$D$14 -> 0.1764 | E20: =E8*1000000/Inputs!$D$14 -> 0.1806 | F20: =F8*1000000/Inputs!$D$14 -> 0.1862 | G20: =G8*1000000/Inputs!$D$14 -> 0.1918 | H20: =H8*1000000/Inputs!$D$14 -> 0.1974 | I20: =I8*1000000/Inputs!$D$14 -> 0.203
A21: =A9 -> 21000 | B21: =B9*1000000/Inputs!$D$14 -> 0.1722 | C21: =C9*1000000/Inputs!$D$14 -> 0.1764 | D21: =D9*1000000/Inputs!$D$14 -> 0.1806 | E21: =E9*1000000/Inputs!$D$14 -> 0.1848 | F21: =F9*1000000/Inputs!$D$14 -> 0.1904 | G21: =G9*1000000/Inputs!$D$14 -> 0.196 | H21: =H9*1000000/Inputs!$D$14 -> 0.2016 | I21: =I9*1000000/Inputs!$D$14 -> 0.2072
A22: =A10 -> 24000 | B22: =B10*1000000/Inputs!$D$14 -> 0.1764 | C22: =C10*1000000/Inputs!$D$14 -> 0.1806 | D22: =D10*1000000/Inputs!$D$14 -> 0.1848 | E22: =E10*1000000/Inputs!$D$14 -> 0.189 | F22: =F10*1000000/Inputs!$D$14 -> 0.1946 | G22: =G10*1000000/Inputs!$D$14 -> 0.2002 | H22: =H10*1000000/Inputs!$D$14 -> 0.2058 | I22: =I10*1000000/Inputs!$D$14 -> 0.2114
A23: =A11 -> 27000 | B23: =B11*1000000/Inputs!$D$14 -> 0.1806 | C23: =C11*1000000/Inputs!$D$14 -> 0.1848 | D23: =D11*1000000/Inputs!$D$14 -> 0.189 | E23: =E11*1000000/Inputs!$D$14 -> 0.1932 | F23: =F11*1000000/Inputs!$D$14 -> 0.1988 | G23: =G11*1000000/Inputs!$D$14 -> 0.2044 | H23: =H11*1000000/Inputs!$D$14 -> 0.21 | I23: =I11*1000000/Inputs!$D$14 -> 0.2156
A24: =A12 -> 30000 | B24: =B12*1000000/Inputs!$D$14 -> 0.1848 | C24: =C12*1000000/Inputs!$D$14 -> 0.189 | D24: =D12*1000000/Inputs!$D$14 -> 0.1932 | E24: =E12*1000000/Inputs!$D$14 -> 0.1974 | F24: =F12*1000000/Inputs!$D$14 -> 0.203 | G24: =G12*1000000/Inputs!$D$14 -> 0.2086 | H24: =H12*1000000/Inputs!$D$14 -> 0.2142 | I24: =I12*1000000/Inputs!$D$14 -> 0.2198
A25: =A13 -> 33000 | B25: =B13*1000000/Inputs!$D$14 -> 0.189 | C25: =C13*1000000/Inputs!$D$14 -> 0.1932 | D25: =D13*1000000/Inputs!$D$14 -> 0.1974 | E25: =E13*1000000/Inputs!$D$14 -> 0.2016 | F25: =F13*1000000/Inputs!$D$14 -> 0.2072 | G25: =G13*1000000/Inputs!$D$14 -> 0.2128 | H25: =H13*1000000/Inputs!$D$14 -> 0.2184 | I25: =I13*1000000/Inputs!$D$14 -> 0.224
A26: =A14 -> 36000 | B26: =B14*1000000/Inputs!$D$14 -> 0.1932 | C26: =C14*1000000/Inputs!$D$14 -> 0.1974 | D26: =D14*1000000/Inputs!$D$14 -> 0.2016 | E26: =E14*1000000/Inputs!$D$14 -> 0.2058 | F26: =F14*1000000/Inputs!$D$14 -> 0.2114 | G26: =G14*1000000/Inputs!$D$14 -> 0.217 | H26: =H14*1000000/Inputs!$D$14 -> 0.2226 | I26: =I14*1000000/Inputs!$D$14 -> 0.2282
A27: =A15 -> 40000 | B27: =B15*1000000/Inputs!$D$14 -> 0.1988 | C27: =C15*1000000/Inputs!$D$14 -> 0.203 | D27: =D15*1000000/Inputs!$D$14 -> 0.2072 | E27: =E15*1000000/Inputs!$D$14 -> 0.2114 | F27: =F15*1000000/Inputs!$D$14 -> 0.217 | G27: =G15*1000000/Inputs!$D$14 -> 0.2226 | H27: =H15*1000000/Inputs!$D$14 -> 0.2282 | I27: =I15*1000000/Inputs!$D$14 -> 0.2338
A29: Reading: even with both spot ships at the bottom-left corner (MR $15k, Kams $10k), the fleet still earns the locked TC income plus a floor — the downside is capped by the 60% fixed cover.
A30: Base case = MR $27,000 × Kams $23,000 cell (row 11, col F).

Sheet Voyage_TCE
A1: Cross-check: last-done Kamsarmax freight rate → daily TCE
A2: Fixture: DBCT (Australia) → Vizag (India), coal 80,000t @ $25.60/t, SAIL, 10 Sep 2026. Yellow = voyage assumptions to confirm.
A4: Item | B4: Value | C4: Basis / source
A5: Cargo (t) | B5: 80000 | C5: Fixture (SIN Fixtures Register, voyage)
A6: Freight rate ($/t) | B6: 25.6 | C6: Fixture (SIN Fixtures Register, voyage)
A7: Gross freight ($) | B7: =B5*B6 -> 2048000
A8: Laden distance (nm) | B8: 4600 | C8: Approx. DBCT → Visakhapatnam via Torres Strait/Lombok — confirm on distance table
A9: Ballast distance (nm) | B9: 4600 | C9: Assume ballast back to Australia (conservative round voyage)
A10: Laden speed (knots) | B10: 12.5 | C10: Eco Kamsarmax service speed
A11: Ballast speed (knots) | B11: 13
A12: Port days (load + discharge + waiting) | B12: 9 | C12: Load 3 + disch 5 + 1 waiting
A13: Sea days | B13: =B8/(B10*24)+B9/(B11*24) -> 30.076923 | C13: Formula
A14: Total voyage days | B14: =B13+B12 -> 39.076923 | C14: Formula
A15: Fuel at sea (t/day) | B15: 27 | C15: Eco Kamsarmax VLSFO consumption
A16: Fuel in port (t/day) | B16: 4
A17: VLSFO price ($/t) | B17: 650 | C17: PLACEHOLDER — replace with Singapore VLSFO price on 10 Sep 2026 (SIN bunker series / Ship & Bunker)
A18: Bunker cost ($) | B18: =(B13*B15+B12*B16)*B17 -> 551250 | C18: Formula
A19: Port costs ($) | B19: 160000 | C19: DBCT + Vizag port/agency estimate
A20: Commission (%) | B20: 0.0375 | C20: 1.25% brokerage + 2.5% address
A21: Commission ($) | B21: =B7*B20 -> 76800 | C21: Formula
A22: Net voyage result ($) | B22: =B7-B18-B19-B21 -> 1259950 | C22: Gross freight − voyage costs
A23: Voyage TCE ($/day) | B23: =B22/B14 -> 32242.815 | C23: Net voyage result ÷ voyage days
A24: Compare: Base spot assumption ($/day) | B24: =Inputs!G9 -> 23000 | C24: Kamsarmax #2 base TCE
A25: Headroom vs base assumption | B25: =B23/B24-1 -> 0.40186152 | C25: Positive = base case is conservative
A31: Interpretation: a full round-voyage TCE above the base $23,000/day means the base case for Kamsarmax #2 is conservative and spot upside sits in the Bull case. Re-check once the bunker price placeholder is replaced.

Sheet Sources
A1: Data sources
A2: All from Clarksons Shipping Intelligence Network (SIN), extracted 12 Sep 2026, unless stated
A4: Item | B4: Source
A5: Time charter fixtures | B5: SIN Fixtures Register (Timecharter): PS Imabari, Challenge Pollux, Torm Genesis, Intensity, XH Hope
A6: Voyage fixtures | B6: SIN Fixtures Register (Voyage/Spot): DBCT→Vizag coal $25.60/t (SAIL); Baltic→USG WS105 (VITOL)
A7: S&P transactions | B7: SIN S&P Register: Southern Reverence, Pusaka Borneo, Aquavita Aim, Medi Positano; MR 5-yr valuation series 47130
A8: OPEX | B8: SIN series 540687 / 540689 / 540683
A9: Spot earnings (to fill) | B9: MR product tanker earnings series 545055 (2025 average); Kamsarmax/Panamax spot earnings (2025 average) — for Bear case
A10: Bunker price (to fill) | B10: Singapore VLSFO price, 10 Sep 2026 — for Voyage_TCE
